mindexer/__init__.py
mindexer/utils/__init__.py
mindexer/utils/mongodb.py
mindexer/utils/query.py
mindexer/utils/sampling.py
mindexer-0.3.0.data/scripts/mindexer
mindexer-0.3.0.dist-info/LICENSE
mindexer-0.3.0.dist-info/METADATA
mindexer-0.3.0.dist-info/WHEEL
mindexer-0.3.0.dist-info/top_level.txt
mindexer-0.3.0.dist-info/RECORD
