Metadata-Version: 2.1
Name: mindexer
Version: 0.3.0
Summary: Experimental Index Recommendation Tool for MongoDB
Home-page: http://github.com/mongodb-labs/mindexer
Author: Thomas Rueckstiess
Author-email: thomas.rueckstiess@mongodb.com
License: MIT
Keywords: mongodb indexes recommendations
License-File: LICENSE
Requires-Dist: numpy
Requires-Dist: pandas
Requires-Dist: pymongo
